rerun_bindings/__init__.py
rerun_bindings/py.typed
rerun_bindings/rerun_bindings.pyd
rerun_bindings/rerun_bindings.pyi
rerun_bindings/types.py
rerun_sdk-0.29.0.dist-info/METADATA
rerun_sdk-0.29.0.dist-info/WHEEL
rerun_sdk-0.29.0.dist-info/entry_points.txt
rerun_sdk.pth
rerun_sdk/rerun/.gitattributes
rerun_sdk/rerun/__init__.py
rerun_sdk/rerun/__main__.py
rerun_sdk/rerun/_arrow.py
rerun_sdk/rerun/_baseclasses.py
rerun_sdk/rerun/_color_conversion.py
rerun_sdk/rerun/_converters.py
rerun_sdk/rerun/_event.py
rerun_sdk/rerun/_legacy_notebook.py
rerun_sdk/rerun/_log.py
rerun_sdk/rerun/_logging_handler.py
rerun_sdk/rerun/_memory.py
rerun_sdk/rerun/_numpy_compatibility.py
rerun_sdk/rerun/_properties.py
rerun_sdk/rerun/_script_helpers.py
rerun_sdk/rerun/_send_columns.py
rerun_sdk/rerun/_send_dataframe.py
rerun_sdk/rerun/_spawn.py
rerun_sdk/rerun/_unions.py
rerun_sdk/rerun/_validators.py
rerun_sdk/rerun/any_batch_value.py
rerun_sdk/rerun/any_value.py
rerun_sdk/rerun/archetypes/.gitattributes
rerun_sdk/rerun/archetypes/__init__.py
rerun_sdk/rerun/archetypes/annotation_context.py
rerun_sdk/rerun/archetypes/arrows2d.py
rerun_sdk/rerun/archetypes/arrows2d_ext.py
rerun_sdk/rerun/archetypes/arrows3d.py
rerun_sdk/rerun/archetypes/arrows3d_ext.py
rerun_sdk/rerun/archetypes/asset3d.py
rerun_sdk/rerun/archetypes/asset3d_ext.py
rerun_sdk/rerun/archetypes/asset_video.py
rerun_sdk/rerun/archetypes/asset_video_ext.py
rerun_sdk/rerun/archetypes/bar_chart.py
rerun_sdk/rerun/archetypes/bar_chart_ext.py
rerun_sdk/rerun/archetypes/boxes2d.py
rerun_sdk/rerun/archetypes/boxes2d_ext.py
rerun_sdk/rerun/archetypes/boxes3d.py
rerun_sdk/rerun/archetypes/boxes3d_ext.py
rerun_sdk/rerun/archetypes/capsules3d.py
rerun_sdk/rerun/archetypes/capsules3d_ext.py
rerun_sdk/rerun/archetypes/clear.py
rerun_sdk/rerun/archetypes/clear_ext.py
rerun_sdk/rerun/archetypes/coordinate_frame.py
rerun_sdk/rerun/archetypes/cylinders3d.py
rerun_sdk/rerun/archetypes/cylinders3d_ext.py
rerun_sdk/rerun/archetypes/depth_image.py
rerun_sdk/rerun/archetypes/depth_image_ext.py
rerun_sdk/rerun/archetypes/ellipsoids3d.py
rerun_sdk-0.29.0.dist-info/RECORD
