Metadata-Version: 2.4
Name: rerun-sdk
Version: 0.29.0
Classifier: Programming Language :: Rust
Classifier: Programming Language :: Python :: Implementation :: CPython
Classifier: Programming Language :: Python :: Implementation :: PyPy
Classifier: Development Status :: 3 - Alpha
Classifier: Topic :: Scientific/Engineering :: Artificial Intelligence
Classifier: Topic :: Scientific/Engineering :: Visualization
Requires-Dist: attrs>=23.1.0
Requires-Dist: numpy>=2
Requires-Dist: pillow>=8.0.0
Requires-Dist: pyarrow>=18.0.0
Requires-Dist: typing-extensions>=4.5
Requires-Dist: inline-snapshot==0.31.1 ; extra == 'tests'
Requires-Dist: opencv-python>4.6 ; extra == 'tests'
Requires-Dist: polars==1.36.1 ; extra == 'tests'
Requires-Dist: pytest==8.4.2 ; extra == 'tests'
Requires-Dist: semver>=3.0,<3.1 ; extra == 'tests'
Requires-Dist: syrupy==5.0.0 ; extra == 'tests'
Requires-Dist: tomli==2.0.1 ; extra == 'tests'
Requires-Dist: torch>=2.5 ; extra == 'tests'
Requires-Dist: datafusion==50.1.0 ; extra == 'tests'
Requires-Dist: rerun-notebook==0.29.0 ; extra == 'notebook'
Requires-Dist: datafusion==50.1.0 ; extra == 'datafusion'
Requires-Dist: rerun-notebook==0.28.0a1+dev ; extra == 'all'
Requires-Dist: datafusion==50.1.0 ; extra == 'all'
Provides-Extra: tests
Provides-Extra: notebook
Provides-Extra: datafusion
Provides-Extra: all
Summary: The Rerun Logging SDK
Keywords: computer-vision,logging,rerun
Author-email: "Rerun.io" <opensource@rerun.io>
License: MIT OR Apache-2.0
Requires-Python: >=3.10
Project-URL: documentation, https://www.rerun.io/docs
Project-URL: homepage, https://www.rerun.io
Project-URL: repository, https://github.com/rerun-io/rerun
